regalias/__init__.py
regalias/__main__.py
regalias/_ndata.py
regalias/about.py
regalias/generate_japanese_alias.py
regalias/generate_japanese_alias_from_rng.py
regalias/generate_japanese_alias_from_str.py
regalias-0.2.0.dist-info/DESCRIPTION.rst
regalias-0.2.0.dist-info/METADATA
regalias-0.2.0.dist-info/RECORD
regalias-0.2.0.dist-info/WHEEL
regalias-0.2.0.dist-info/entry_points.txt
regalias-0.2.0.dist-info/metadata.json
regalias-0.2.0.dist-info/top_level.txt
