Metadata-Version: 2.0
Name: regalias
Version: 0.2.0
Summary: Elona-like alias generator for Python, with CLI.
Home-page: https://github.com/letla/regalias
Author: Letla Fox
Author-email: letlafox+pypi@gmail.com
License: Apache 2.0
Platform: UNKNOWN
Classifier: Development Status :: 4 - Beta
Classifier: Environment :: Console
Classifier: License :: OSI Approved :: Apache Software License
Classifier: Natural Language :: Japanese
Classifier: Programming Language :: Python
Classifier: Programming Language :: Python :: 3
Classifier: Programming Language :: Python :: 3.5
Classifier: Programming Language :: Python :: 3 :: Only
Classifier: Programming Language :: Python :: Implementation :: CPython
Classifier: Topic :: Games/Entertainment :: Role-Playing
Classifier: Topic :: Text Processing
Classifier: Topic :: Text Processing :: Filters
